{
    "header" : "00IMBARQ0010010000359BVMF    0000000000003590000000012020012420200123                                                                                                                                                                                                                                                                                                                                                                                                                                                                                                                                                                                                                                                                                                                                                                                                                                                                                                                                                                   ",
    "body" : [ {
      "line" : "26359            1105           5359            1105           21016CARTEIRA LIVRE BRLRENACNOR1194LOJAS RENNERON      NM00000000014000000020190318201903220010875632019000000000000000000013012300000001013JUROS SOBRE CAPITAL 00000000000000000000000000000000000000000000000000002602460                                                                                                                                                                                                                                                                                                                                                                                                                                                                                                                                                                                                                                                                                                                                              ",
      "TipoDeRegistro" : "26",
      "CodigoDoParticipanteSolicitante" : "359            ",
      "CodigoDoInvestidorSolicitante" : "1105           ",
      "DigitoDoInvestidorSolicitante" : "5",
      "CodigoDoParticipanteSolicitado" : "359            ",
      "CodigoDoInvestidorSolicitado" : "1105           ",
      "CodigoDaCarteira" : "21016",
      "DescricaoDaCarteira" : "CARTEIRA LIVRE ",
      "CodigoIsinDaBase" : "BRLRENACNOR1",
      "DistribuicaoDaBase" : "194",
      "NomeDaSociedadeEmissora-Base" : "LOJAS RENNER",
      "Especificacao" : "ON      NM",
      "QuantidadeDeAcoesBase" : "000000000140000000",
      "DataAge" : "20190318",
      "DataDeInicioDoProvento" : "20190322",
      "NumeroDoProcesso" : "001087563",
      "AnoDeReferenciaDoExercicio" : "2019",
      "DataPrevistaPPagamentoDividendo" : "00000000",
      "ValorBrutoDoDividendo" : "000000000001301230",
      "PercentualDoImpostoDeRenda" : "00000",
      "CodigoDoImpostoDeRenda" : "0",
      "InstituicaoPagadora" : "1",
      "TipoDeProvento" : "013",
      "DescricaoDoProvento" : "JUROS SOBRE CAPITAL ",
      "DataAquisicao" : "00000000",
      "PrecoDaAquisicao" : "000000000000000",
      "Reserva" : "000000000000000000000000000002602460                                                                                                                                                                                                                                                                                                                                                                                                                                                                                                                                                                                                                                                                                                                                              "
    }, {
      "line" : "26359            1105           5359            1105           21016CARTEIRA LIVRE BRLRENACNOR1199LOJAS RENNERON      NM00000000021500000020191218201912260010916052019000000000000000000013012300000001013JUROS SOBRE CAPITAL 00000000000000000000000000000000000000000000000000001661477                                                                                                                                                                                                                                                                                                                                                                                                                                                                                                                                                                                                                                                                                                                                              ",
      "TipoDeRegistro" : "26",
      "CodigoDoParticipanteSolicitante" : "359            ",
      "CodigoDoInvestidorSolicitante" : "1105           ",
      "DigitoDoInvestidorSolicitante" : "5",
      "CodigoDoParticipanteSolicitado" : "359            ",
      "CodigoDoInvestidorSolicitado" : "1105           ",
      "CodigoDaCarteira" : "21016",
      "DescricaoDaCarteira" : "CARTEIRA LIVRE ",
      "CodigoIsinDaBase" : "BRLRENACNOR1",
      "DistribuicaoDaBase" : "199",
      "NomeDaSociedadeEmissora-Base" : "LOJAS RENNER",
      "Especificacao" : "ON      NM",
      "QuantidadeDeAcoesBase" : "000000000215000000",
      "DataAge" : "20191218",
      "DataDeInicioDoProvento" : "20191226",
      "NumeroDoProcesso" : "001091605",
      "AnoDeReferenciaDoExercicio" : "2019",
      "DataPrevistaPPagamentoDividendo" : "00000000",
      "ValorBrutoDoDividendo" : "000000000001301230",
      "PercentualDoImpostoDeRenda" : "00000",
      "CodigoDoImpostoDeRenda" : "0",
      "InstituicaoPagadora" : "1",
      "TipoDeProvento" : "013",
      "DescricaoDoProvento" : "JUROS SOBRE CAPITAL ",
      "DataAquisicao" : "00000000",
      "PrecoDaAquisicao" : "000000000000000",
      "Reserva" : "000000000000000000000000000001661477                                                                                                                                                                                                                                                                                                                                                                                                                                                                                                                                                                                                                                                                                                                                              "
    }, {
      "line" : "26359            1105           5359            1105           21016CARTEIRA LIVRE BRLRENACNOR1198LOJAS RENNERON      NM00000000027000000020190919201909250010901912019000000000000000000021218760000001013JUROS SOBRE CAPITAL 00000000000000000000000000000000000000000000000000002121876                                                                                                                                                                                                                                                                                                                                                                                                                                                                                                                                                                                                                                                                                                                                              ",
      "TipoDeRegistro" : "26",
      "CodigoDoParticipanteSolicitante" : "359            ",
      "CodigoDoInvestidorSolicitante" : "1105           ",
      "DigitoDoInvestidorSolicitante" : "5",
      "CodigoDoParticipanteSolicitado" : "359            ",
      "CodigoDoInvestidorSolicitado" : "1105           ",
      "CodigoDaCarteira" : "21016",
      "DescricaoDaCarteira" : "CARTEIRA LIVRE ",
      "CodigoIsinDaBase" : "BRLRENACNOR1",
      "DistribuicaoDaBase" : "198",
      "NomeDaSociedadeEmissora-Base" : "LOJAS RENNER",
      "Especificacao" : "ON      NM",
      "QuantidadeDeAcoesBase" : "000000000270000000",
      "DataAge" : "20190919",
      "DataDeInicioDoProvento" : "20190925",
      "NumeroDoProcesso" : "001090191",
      "AnoDeReferenciaDoExercicio" : "2019",
      "DataPrevistaPPagamentoDividendo" : "00000000",
      "ValorBrutoDoDividendo" : "000000000002121876",
      "PercentualDoImpostoDeRenda" : "00000",
      "CodigoDoImpostoDeRenda" : "0",
      "InstituicaoPagadora" : "1",
      "TipoDeProvento" : "013",
      "DescricaoDoProvento" : "JUROS SOBRE CAPITAL ",
      "DataAquisicao" : "00000000",
      "PrecoDaAquisicao" : "000000000000000",
      "Reserva" : "000000000000000000000000000002121876                                                                                                                                                                                                                                                                                                                                                                                                                                                                                                                                                                                                                                                                                                                                              "
    } ],
    "footer" : "99IMBARQ0010010000359BVMF    0000000000003590000000012020012400000395920200123                                                                                                                                                                                                                                                                                                                                                                                                                                                                                                                                                                                                                                                                                                                                                                                                                                                                                                                                                          "
  }  